sentinelsat/__init__.py
sentinelsat/__main__.py
sentinelsat/download.py
sentinelsat/exceptions.py
sentinelsat/products.py
sentinelsat/sentinel.py
sentinelsat/scripts/__init__.py
sentinelsat/scripts/cli.py
frx08_sentinelsat-1.2.2.dist-info/AUTHORS.rst
frx08_sentinelsat-1.2.2.dist-info/LICENSE
frx08_sentinelsat-1.2.2.dist-info/METADATA
frx08_sentinelsat-1.2.2.dist-info/WHEEL
frx08_sentinelsat-1.2.2.dist-info/entry_points.txt
frx08_sentinelsat-1.2.2.dist-info/top_level.txt
frx08_sentinelsat-1.2.2.dist-info/zip-safe
frx08_sentinelsat-1.2.2.dist-info/RECORD
