Metadata-Version: 2.1
Name: frx08-sentinelsat
Version: 1.2.2
Summary: Utility to search and download Copernicus Sentinel satellite images
Home-page: https://github.com/sentinelsat/sentinelsat
Author: Kersten Clauss
Author-email: sentinelsat@krstn.eu
License: GPLv3+
Keywords: copernicus,sentinel,esa,satellite,download,GIS
Classifier: License :: OSI Approved :: GNU General Public License v3 or later (GPLv3+)
Classifier: Programming Language :: Python :: 3
Classifier: Programming Language :: Python :: 3.6
Classifier: Programming Language :: Python :: 3.7
Classifier: Programming Language :: Python :: 3.8
Classifier: Programming Language :: Python :: 3.9
Classifier: Programming Language :: Python :: 3.10
Classifier: Programming Language :: Python :: 3.11
Classifier: Topic :: Scientific/Engineering :: GIS
Classifier: Topic :: Utilities
License-File: LICENSE
License-File: AUTHORS.rst
Requires-Dist: requests
Requires-Dist: click (>=7.1)
Requires-Dist: html2text
Requires-Dist: geojson (>=2)
Requires-Dist: tqdm (>=4.58)
Requires-Dist: geomet
Provides-Extra: dev
Requires-Dist: pandas ; extra == 'dev'
Requires-Dist: geopandas ; extra == 'dev'
Requires-Dist: shapely ; extra == 'dev'
Requires-Dist: pytest (>=3.6.3) ; extra == 'dev'
Requires-Dist: pytest-vcr ; extra == 'dev'
Requires-Dist: pytest-socket ; extra == 'dev'
Requires-Dist: requests-mock ; extra == 'dev'
Requires-Dist: pyyaml ; extra == 'dev'
Requires-Dist: rstcheck (<6) ; extra == 'dev'
Requires-Dist: sphinx (>=1.3) ; extra == 'dev'
Requires-Dist: sphinx-rtd-theme ; extra == 'dev'
Requires-Dist: flaky ; extra == 'dev'
